{
  "title": "PEACE PERFECT PEACE",
  "index": 210,
  "content": {
    "type": "verses_only",
    "verses": [
      "Peace, Perfect peace, in this dark world of sin\nThe blood of Jesus whispers peace within.",
      "Peace, perfect peace, by thronging duties pressed?\nTo do the will of Jesus this is test.",
      "Peace, perfect peace, with sorrows surging round?\non Jesus bosom naught but calm is found.",
      "Peace perfect peace, with loved ones far away\nIn Jesus keeping we are safe, and they.",
      "Peace, perfect peace, our future all unknown?\nJesus we know, and He is on the throne.",
      "Peace, perfect peace, death shadowing us and ours?\nJesus has vanquished death and all its powers.",
      "It is enough; earth's struggles soon shall cease,\nAnd Jesus call us to heaven s Perfect peace."
    ]
  }
}
