{
  "title": "GI BU CHUKWU",
  "index": 57,
  "content": {
    "type": "chorus_and_verses",
    "chorus": "Gi bu Chukwu Gi kere madu nile\nGi bu ugwo ndu ha",
    "verses": [
      "Dinwenu gi bu ihe nke m\nGi bu onye nzoputam\nDinwenu gi bu mgbodo nke m\nOnye ka m ga atu egwu?",
      "Ndi ajo mmadun'abia\nka ha mekpa m'ahu\nDinwenu gi bu mgbodo nke m\nGi ga akwatu ndi irom.",
      "Otu ihe ka mn'iro gi\nDinwenu m na Chukwu mn\nKa m biri n'ime ulo Gi\nubochi niile nke ndum.",
      "Aga mn'ekwe n'eto Gi\nChukwu nuru olu nkem\nZitara m onyinye Gi\nNke I g'eji gbaa m ume.",
      "Ajukwala m n'iwe Gi,\nSo Gi bu Onye inye aka m\nKuziere m uzo Gi, Dinwenu O\nChukwu nara anyi",
      "Otito diri Gi Nna, Otito diri Nwa\nOtito diri Muo Nso uwatuwa niile\nA-men."
    ]
  }
}
