{
  "title": "YA ALLAH UBANMU",
  "index": 83,
  "content": {
    "type": "verses_only",
    "verses": [
      "Ya Allah ubanmu ga mu adurkushe\nA gabanka kaji adduarmu\nYa Allah ubanmu ga mu adurkushe,\nA gabanka kaji adduarmu",
      "Ya Allah ka aiko, da darka Jesu\nYa zo ya mutu domin zunubamu\nYa Allah kal aiko, da danka Jesu,",
      "Yesu ya sha wahala, har yamutu,\nA kan giciye, domin zunubamu\nYesu ya sha wahala' har ya mutu,\nA kan gciye domin mu.",
      "Ya Allah ban isaba, ku shiga wurinaba,\nAmma ka ya Magana, ruhuna zal warke\nVa Allah ban isaba, ku shiga wurinaba\nAmma ka ya magana, ruhuna zai warke"
    ]
  }
}
