{
  "title": "ANYI ABIAWO CHINEKE",
  "index": 22,
  "content": {
    "type": "chorus_and_verses",
    "chorus": "Anyi abiawo Chineke anyi abiawo Nna\nAnyi abiawo ikele gi gozie anyl Chukwu",
    "verses": [
      "Bianu umu Chineke k'anyi kelee Nna\nBianu ndi kwere na okpara ya Jesu",
      "Too nu Chneke Onye kere uwa nile\nToonu Chineke Onye n'echekwa-ba ya",
      "Chukwu ebuka, Chukwu ebuka\nNgozi ya kari akari n'ebe anyi no\nKelee ya, kelee ya, kelenu Chukwu.",
      "Gi bu Nna Nw'ekele anyi m'ututu m'ehihie\nGi bu Nna nw'otito anyi ma mgbede m'anyasi."
    ]
  }
}
