{
  "title": "YES, I SHALL ARISE",
  "index": 6,
  "content": {
    "type": "chorus_and_verses",
    "chorus": "Yes, I shall arise, and return to my father (2ice)",
    "verses": [
      "To You, O Lord, I lift up my soul,\nIn You O my God, I place all my trust.",
      "Look down on me, have mercy, O Lord;\nForgive me my sins, behold all my grief.",
      "My heart and soul shall yearn for your face,\nBe gracious to me and answer my plea.",
      "Do not with hold Your goodness from me\nO Lord, may your love be deep in my soul.",
      "To You I pray, have pity on me;\nMy God, I have sinned against You great love.",
      "Mercy I cry, O Lord, wash me clean;\nAnd whiter than snow my spirit shall be.",
      "Give me again the joy of Your help,\nNow open my lips, your praise I will sing.",
      "Happy is he, forgiven by God;\nHis sins blotted out, his guilt is no more",
      "You are my joy, my refuge and strength;\nLet all upright hearts give praise to the Lord.",
      "My soul will sing; my heart will rejoice;\nThe blessings of God will fill all my days"
    ]
  }
}
